django_commands/__about__.py
django_commands/__about__.py.orig
django_commands/__init__.py
django_commands/admin.py
django_commands/apps.py
django_commands/argument_types.py
django_commands/commands.py
django_commands/exceptions.py
django_commands/mixins.py
django_commands/models.py
django_commands/py.typed
django_commands/tasks.py
django_commands/urls.py
django_commands/utils.py
django_commands/utils.py.orig
django_commands/views.py
django_commands/management/__init__.py
django_commands/management/commands/__init__.py
django_commands/management/commands/slow_command.py
django_commands/management/commands/test_datetime_option.py
django_commands/management/commands/test_wait_commands.py
django_commands/management/commands/test_warm_shutdown.py
django_commands/migrations/0001_initial.py
django_commands/migrations/__init__.py
django_commands/tests/__init__.py
django_commands/tests/test_commands.py
django_commands2-0.26.0.dist-info/METADATA
django_commands2-0.26.0.dist-info/WHEEL
django_commands2-0.26.0.dist-info/licenses/LICENSE.txt
django_commands2-0.26.0.dist-info/RECORD
