Metadata-Version: 2.3
Name: django-commands2
Version: 0.26.0
Project-URL: Documentation, https://github.com/ramwin/django-commands#readme
Project-URL: Issues, https://github.com/ramwin/django-commands/issues
Project-URL: Source, https://github.com/ramwin/django-commands
Author-email: Xiang Wang <ramwin@qq.com>
Classifier: Development Status :: 4 - Beta
Classifier: Programming Language :: Python
Classifier: Programming Language :: Python :: 3.7
Classifier: Programming Language :: Python :: 3.8
Classifier: Programming Language :: Python :: 3.9
Classifier: Programming Language :: Python :: 3.10
Classifier: Programming Language :: Python :: 3.11
Classifier: Programming Language :: Python :: Implementation :: CPython
Classifier: Programming Language :: Python :: Implementation :: PyPy
Requires-Python: >=3.7
Requires-Dist: celery
Requires-Dist: django
Requires-Dist: djangorestframework
Requires-Dist: portion
